featurefilm/__init__.py
featurefilm/__main__.py
featurefilm/player_test.py
featurefilm/writer_test.py
featurefilm/models/face_detection_yunet_2023mar.onnx
featurefilm-2023.11.17.dist-info/LICENSE
featurefilm-2023.11.17.dist-info/METADATA
featurefilm-2023.11.17.dist-info/WHEEL
featurefilm-2023.11.17.dist-info/entry_points.txt
featurefilm-2023.11.17.dist-info/top_level.txt
featurefilm-2023.11.17.dist-info/RECORD
